[{"county": "Alba", "value": -15.26, "id": 1.0}, {"county": "Arad", "value": -15.67, "id": 2.0}, {"county": "Arge\u0219", "value": -15.88, "id": 3.0}, {"county": "Bac\u0103u", "value": -15.29, "id": 4.0}, {"county": "Bihor", "value": -16.02, "id": 5.0}, {"county": "Bistri\u021ba-N\u0103s\u0103ud", "value": -14.77, "id": 6.0}, {"county": "Boto\u0219ani", "value": -13.27, "id": 7.0}, {"county": "Br\u0103ila", "value": -13.56, "id": 9.0}, {"county": "Bra\u0219ov", "value": -15.48, "id": 8.0}, {"county": "Bucure\u0219ti", "value": -14.7, "id": 10.0}, {"county": "Buz\u0103u", "value": -14.04, "id": 11.0}, {"county": "C\u0103l\u0103ra\u0219i", "value": -11.8, "id": 12.0}, {"county": "Cara\u0219-Severin", "value": -15.92, "id": 13.0}, {"county": "Cluj", "value": -14.04, "id": 14.0}, {"county": "Constan\u021ba", "value": -16.95, "id": 15.0}, {"county": "Covasna", "value": -14.39, "id": 16.0}, {"county": "D\u00e2mbovi\u021ba", "value": -15.63, "id": 17.0}, {"county": "Dolj", "value": -13.98, "id": 18.0}, {"county": "Gala\u021bi", "value": -13.92, "id": 19.0}, {"county": "Giurgiu", "value": -12.87, "id": 20.0}, {"county": "Gorj", "value": -15.11, "id": 21.0}, {"county": "Harghita", "value": -14.74, "id": 22.0}, {"county": "Hunedoara", "value": -15.41, "id": 23.0}, {"county": "Ialomi\u021ba", "value": -13.5, "id": 25.0}, {"county": "Ia\u0219i", "value": -13.58, "id": 24.0}, {"county": "Ilfov", "value": -18.47, "id": 26.0}, {"county": "Maramure\u0219", "value": -15.63, "id": 27.0}, {"county": "Mehedin\u021bi", "value": -12.78, "id": 28.0}, {"county": "Mure\u0219", "value": -15.02, "id": 29.0}, {"county": "Neam\u021b", "value": -14.91, "id": 30.0}, {"county": "Olt", "value": -12.23, "id": 31.0}, {"county": "Prahova", "value": -15.85, "id": 32.0}, {"county": "S\u0103laj", "value": -14.73, "id": 33.0}, {"county": "Satu Mare", "value": -14.09, "id": 34.0}, {"county": "Sibiu", "value": -15.82, "id": 35.0}, {"county": "Suceava", "value": -14.81, "id": 36.0}, {"county": "Teleorman", "value": -13.01, "id": 37.0}, {"county": "Timi\u0219", "value": -14.6, "id": 38.0}, {"county": "Tulcea", "value": -13.06, "id": 39.0}, {"county": "V\u00e2lcea", "value": -15.65, "id": 40.0}, {"county": "Vaslui", "value": -11.73, "id": 41.0}, {"county": "Vrancea", "value": -13.57, "id": 42.0}]